a_selenium_scroll_down_forever/LICENSE
a_selenium_scroll_down_forever/README.MD
a_selenium_scroll_down_forever/__init__.py
a_selenium_scroll_down_forever/requirements.txt
a_selenium_scroll_down_forever/thirdparty.json
a_selenium_scroll_down_forever-0.10.dist-info/LICENSE.rst
a_selenium_scroll_down_forever-0.10.dist-info/METADATA
a_selenium_scroll_down_forever-0.10.dist-info/WHEEL
a_selenium_scroll_down_forever-0.10.dist-info/top_level.txt
a_selenium_scroll_down_forever-0.10.dist-info/RECORD
